unofficial_pokedex_folder/unofficial-pokedex-main/CHANGELOG.txt
unofficial_pokedex_folder/unofficial-pokedex-main/__init__.py
unofficial_pokedex_folder/unofficial-pokedex-main/launch_pokedex_program.py
unofficial_pokedex_folder/unofficial-pokedex-main/requirements.txt
unofficial_pokedex_folder/unofficial-pokedex-main/modules/__init__.py
unofficial_pokedex_folder/unofficial-pokedex-main/modules/ability_module.py
unofficial_pokedex_folder/unofficial-pokedex-main/modules/attack_module.py
unofficial_pokedex_folder/unofficial-pokedex-main/modules/height_weight_module.py
unofficial_pokedex_folder/unofficial-pokedex-main/modules/misc_module.py
unofficial_pokedex_folder/unofficial-pokedex-main/modules/sound_module.py
unofficial_pokedex_folder/unofficial-pokedex-main/modules/text_updates.py
unofficial_pokedex_folder/unofficial-pokedex-main/modules/type_module.py
unofficial_pokedex_folder/unofficial-pokedex-main/modules/assets/abilities.png
unofficial_pokedex_folder/unofficial-pokedex-main/modules/assets/abilitiesh.png
unofficial_pokedex_folder/unofficial-pokedex-main/modules/assets/abilitiesp.png
unofficial_pokedex_folder/unofficial-pokedex-main/modules/assets/attacks.png
unofficial_pokedex_folder/unofficial-pokedex-main/modules/assets/attacksh.png
unofficial_pokedex_folder/unofficial-pokedex-main/modules/assets/attacksh2.png
unofficial_pokedex_folder/unofficial-pokedex-main/modules/assets/attacksp.png
unofficial_pokedex_folder/unofficial-pokedex-main/modules/assets/back.png
unofficial_pokedex_folder/unofficial-pokedex-main/modules/assets/backh.png
unofficial_pokedex_folder/unofficial-pokedex-main/modules/assets/backp.png
unofficial_pokedex_folder/unofficial-pokedex-main/modules/assets/bug.png
unofficial_pokedex_folder/unofficial-pokedex-main/modules/assets/bugh.png
unofficial_pokedex_folder/unofficial-pokedex-main/modules/assets/bugp.png
unofficial_pokedex_folder/unofficial-pokedex-main/modules/assets/button.png
unofficial_pokedex-0.0.9.dist-info/METADATA
unofficial_pokedex-0.0.9.dist-info/WHEEL
unofficial_pokedex-0.0.9.dist-info/licenses/LICENSE.txt
unofficial_pokedex-0.0.9.dist-info/RECORD
