Metadata-Version: 2.1
Name: unofficial_pokedex
Version: 0.0.9
Summary: A python based Pokédex with a PyQt GUI.
Project-URL: Homepage, https://github.com/nkocodes/unofficial-pokedex
Project-URL: Bug Tracker, https://github.com/nkocodes/unofficial-pokedex/issues
Author-email: Nader Omar <nkocontact@proton.me>
License-File: LICENSE.txt
Classifier: License :: OSI Approved :: MIT License
Classifier: Operating System :: OS Independent
Classifier: Programming Language :: Python :: 3
Requires-Python: >=3.8
Requires-Dist: playsound==1.2.2
Requires-Dist: pygame==2.1.2
Requires-Dist: pyqt6==6.4.0
Requires-Dist: requests==2.28.1
